gcloud_taskqueue/__init__.py
gcloud_taskqueue/client.py
gcloud_taskqueue/connection.py
gcloud_taskqueue/task.py
gcloud_taskqueue/taskqueue.py
gcloud_taskqueue-0.1.2.dist-info/DESCRIPTION.rst
gcloud_taskqueue-0.1.2.dist-info/METADATA
gcloud_taskqueue-0.1.2.dist-info/RECORD
gcloud_taskqueue-0.1.2.dist-info/WHEEL
gcloud_taskqueue-0.1.2.dist-info/metadata.json
gcloud_taskqueue-0.1.2.dist-info/top_level.txt
gcloud_taskqueue-0.1.2.dist-info/zip-safe
