Metadata-Version: 2.0
Name: gcloud-taskqueue
Version: 0.1.2
Summary: Interface for TaskQueue
Home-page: https://github.com/sebastiancodes/gcloud_taskqueue
Author: Bas van den Broek
Author-email: cwasvandenbroek@gmail.com
License: Apache License, Version 2.0
Keywords: google-api-python-client google-gcloud gcloud google-taskqueue taskqueue
Platform: UNKNOWN
Classifier: Development Status :: 3 - Alpha
Classifier: Intended Audience :: Developers
Classifier: Topic :: Software Development :: Build Tools
Classifier: License :: OSI Approved :: Apache Software License
Classifier: Programming Language :: Python :: 2.7
Classifier: Programming Language :: Python :: 3.4
Classifier: Programming Language :: Python :: 3.5
Requires-Dist: gcloud
